MANIFEST.in
README.md
setup.py
my_names_mpasierb.egg-info/PKG-INFO
my_names_mpasierb.egg-info/SOURCES.txt
my_names_mpasierb.egg-info/dependency_links.txt
my_names_mpasierb.egg-info/requires.txt
my_names_mpasierb.egg-info/top_level.txt
my_names_pac/__init__.py
my_names_pac/my_names.py