Metadata-Version: 2.1
Name: my-names-mpasierb
Version: 1.0.0
Summary: Generate random names with length
Home-page: UNKNOWN
Author: Malgorzata Pasierb
Author-email: m.pasierb90@gmail.com
License: UNKNOWN
Keywords: random names
Platform: UNKNOWN
